{
  "count": 1,
  "duplicates": [
    {
      "token": "Pvyhb0Ti3olFXhxHFlUcBgDoneh",
      "title": "2025 破浪欧亚中国企业出海之消费者及市场洞察报告试阅版 尼尔森IQ",
      "summary": "破浪欧亚中国企业出海之消费者及市场洞察报告试阅版 尼尔森IQ（数据来源：尼尔森）",
      "tags": [
        "消费洞察",
        "跨境电商",
        "消费者研究",
        "消费趋势"
      ],
      "score": 88,
      "year": "2025",
      "date": "2025",
      "url": "https://my.feishu.cn/file/Pvyhb0Ti3olFXhxHFlUcBgDoneh",
      "type": "file",
      "size": 0,
      "created_time": "2026-05-26",
      "modified_time": "2026-05-26",
      "month": "",
      "source": "尼尔森",
      "_dup_reason": "标题相似去重(key=破浪欧亚中国企业出海之消费者及市场洞察报告试阅版尼尔森iq... 同年=2025)",
      "_dup_of": "2025 破浪欧亚中国企业出海之消费者及市场洞察报告试阅版64页 尼尔森IQ"
    }
  ]
}