{
  "categories": [
    "大健康",
    "小红书",
    "抖音",
    "TikTok",
    "营销方案",
    "品牌手册",
    "美妆个护",
    "宠物经济",
    "服饰时尚",
    "食品饮料",
    "母婴亲子",
    "家居生活",
    "快消零售",
    "奢侈品",
    "香氛",
    "户外运动",
    "跨境电商",
    "其他"
  ],
  "total_files": 9649,
  "dup_removed": 0,
  "updated": "2026-05-27 13:01:30",
  "counts": {
    "大健康": 407,
    "小红书": 568,
    "抖音": 221,
    "TikTok": 77,
    "营销方案": 279,
    "品牌手册": 392,
    "美妆个护": 515,
    "宠物经济": 69,
    "服饰时尚": 66,
    "食品饮料": 162,
    "母婴亲子": 93,
    "家居生活": 132,
    "快消零售": 93,
    "奢侈品": 23,
    "香氛": 30,
    "户外运动": 77,
    "跨境电商": 210,
    "其他": 6235
  }
}