{
  "category": "户外运动",
  "count": 5,
  "dup_removed": 0,
  "files": [
    {
      "token": "42f874c6a32149c2ad24e14ff3f63815",
      "title": "24年10月运动健身行业爆文Top500",
      "summary": "24年10月运动健身行业爆文Top500",
      "tags": [
        "行业报告"
      ],
      "score": 50,
      "year": "未知",
      "date": "未知",
      "url": "https://pan.quark.cn/s/a6333ce223e9",
      "type": "file",
      "size": 237412,
      "created_time": 1779778602857,
      "modified_time": 1779778602857,
      "month": "",
      "source": ""
    },
    {
      "token": "5253d759474b46faae64f24d21a3749c",
      "title": "24年11月运动健身行业爆文Top500",
      "summary": "24年11月运动健身行业爆文Top500",
      "tags": [
        "行业报告"
      ],
      "score": 50,
      "year": "未知",
      "date": "未知",
      "url": "https://pan.quark.cn/s/82afd7ef151b",
      "type": "file",
      "size": 243783,
      "created_time": 1779778602506,
      "modified_time": 1779778602506,
      "month": "",
      "source": ""
    },
    {
      "token": "23475b8e04de451db4dbd813071d8261",
      "title": "24年12月运动健身行业爆文Top500",
      "summary": "24年12月运动健身行业爆文Top500",
      "tags": [
        "行业报告"
      ],
      "score": 50,
      "year": "未知",
      "date": "未知",
      "url": "https://pan.quark.cn/s/017ad9a5db08",
      "type": "file",
      "size": 284989,
      "created_time": 1779778602620,
      "modified_time": 1779778602620,
      "month": "",
      "source": ""
    },
    {
      "token": "0b065a5eee08448cab0eaffd50ec24f0",
      "title": "25年1月运动健身行业爆文Top500",
      "summary": "25年1月运动健身行业爆文Top500",
      "tags": [
        "行业报告"
      ],
      "score": 50,
      "year": "未知",
      "date": "未知",
      "url": "https://pan.quark.cn/s/0934caf0e3c6",
      "type": "file",
      "size": 292136,
      "created_time": 1779778602815,
      "modified_time": 1779778602815,
      "month": "",
      "source": ""
    },
    {
      "token": "47838d23582f4ef684702df1694175ed",
      "title": "88全民健身打卡招商通案(1)",
      "summary": "88全民健身打卡招商通案(1)",
      "tags": [
        "行业报告"
      ],
      "score": 50,
      "year": "未知",
      "date": "未知",
      "url": "https://pan.quark.cn/s/9cac0bbc719f",
      "type": "file",
      "size": 8726217,
      "created_time": 1741664638693,
      "modified_time": 1741664638693,
      "month": "",
      "source": ""
    }
  ],
  "updated": "2026-05-26 15:28:02"
}